<annotation>
	<folder></folder>
	<filename>18_png.rf.fbfb79ff9c8e8e489afa0f7919dd96ae.jpg</filename>
	<path>18_png.rf.fbfb79ff9c8e8e489afa0f7919dd96ae.jpg</path>
	<source>
		<database>roboflow.com</database>
	</source>
	<size>
		<width>640</width>
		<height>640</height>
		<depth>3</depth>
	</size>
	<segmented>0</segmented>
	<object>
		<name>Speed limit 30</name>
		<pose>Unspecified</pose>
		<truncated>0</truncated>
		<difficult>0</difficult>
		<occluded>0</occluded>
		<bndbox>
			<xmin>52</xmin>
			<xmax>590</xmax>
			<ymin>1</ymin>
			<ymax>596</ymax>
		</bndbox>
	</object>
</annotation>
